README.rst
setup.py
anderssontree/__init__.py
anderssontree/anderssontree.py
anderssontree.egg-info/PKG-INFO
anderssontree.egg-info/SOURCES.txt
anderssontree.egg-info/dependency_links.txt
anderssontree.egg-info/top_level.txt
test/test_aatree.py