Metadata-Version: 1.1
Name: anderssontree
Version: 0.1.0
Summary: Package provides Andersson Tree implementation in pure Python.
Home-page: https://github.com/darko-poljak/anderssontree
Author: Darko Poljak
Author-email: darko.poljak@gmail.com
License: GPLv3
Download-URL: https://github.com/darko-poljak/anderssontree
Keywords: AA Tree,Andersson Tree
Platform: OS Independent
Classifier: Development Status :: 4 - Beta
Classifier: License :: OSI Approved :: GNU General Public License v3 (GPLv3)
Classifier: Operating System :: OS Independent
Classifier: Topic :: Software Development :: Libraries :: Python Modules
